<?xml version="1.0" encoding="UTF-8"?>
<!DOCTYPE mapper PUBLIC "-//mybatis.org//DTD Mapper 3.0//EN" "http://mybatis.org/dtd/mybatis-3-mapper.dtd">
<mapper namespace="com.deal.mrzhang.deal.mapper.QuestionDetailMapper">
  <resultMap id="BaseResultMap" type="com.deal.mrzhang.deal.entity.QuestionDetail">
    <!--
      WARNING - @mbg.generated
      This element is automatically generated by MyBatis Generator, do not modify.
    -->
    <id column="id" jdbcType="INTEGER" property="id" />
    <result column="descs" jdbcType="VARCHAR" property="descs" />
    <result column="solution" jdbcType="VARCHAR" property="solution" />
    <result column="create_date" jdbcType="DATE" property="createDate" />
    <result column="create_time" jdbcType="VARCHAR" property="createTime" />
    <result column="type_id" jdbcType="INTEGER" property="typeId" />
    <result column="type_name" jdbcType="VARCHAR" property="typeName" />
    <result column="first_type_id" jdbcType="INTEGER" property="firstTypeId" />
    <result column="first_type_name" jdbcType="VARCHAR" property="firstTypeName" />
    <result column="second_type_id" jdbcType="INTEGER" property="secondTypeId" />
    <result column="second_type_name" jdbcType="VARCHAR" property="secondTypeName" />
    <result column="thrid_type_id" jdbcType="INTEGER" property="thridTypeId" />
    <result column="thrid_type_name" jdbcType="VARCHAR" property="thridTypeName" />
    <result column="source_id" jdbcType="INTEGER" property="sourceId" />
    <result column="source_name" jdbcType="VARCHAR" property="sourceName" />
    <result column="creator" jdbcType="VARCHAR" property="creator" />
    <result column="class_id" jdbcType="VARCHAR" property="classId" />
    <result column="location" jdbcType="VARCHAR" property="location" />
    <result column="live_room" jdbcType="VARCHAR" property="liveRoom" />
    <result column="resolvor" jdbcType="VARCHAR" property="resolvor" />
  </resultMap>
  <sql id="Example_Where_Clause">
    <!--
      WARNING - @mbg.generated
      This element is automatically generated by MyBatis Generator, do not modify.
    -->
    <where>
      <foreach collection="oredCriteria" item="criteria" separator="or">
        <if test="criteria.valid">
          <trim prefix="(" prefixOverrides="and" suffix=")">
            <foreach collection="criteria.criteria" item="criterion">
              <choose>
                <when test="criterion.noValue">
                  and ${criterion.condition}
                </when>
                <when test="criterion.singleValue">
                  and ${criterion.condition} #{criterion.value}
                </when>
                <when test="criterion.betweenValue">
                  and ${criterion.condition} #{criterion.value} and #{criterion.secondValue}
                </when>
                <when test="criterion.listValue">
                  and ${criterion.condition}
                  <foreach close=")" collection="criterion.value" item="listItem" open="(" separator=",">
                    #{listItem}
                  </foreach>
                </when>
              </choose>
            </foreach>
          </trim>
        </if>
      </foreach>
    </where>
  </sql>
  <sql id="Update_By_Example_Where_Clause">
    <!--
      WARNING - @mbg.generated
      This element is automatically generated by MyBatis Generator, do not modify.
    -->
    <where>
      <foreach collection="example.oredCriteria" item="criteria" separator="or">
        <if test="criteria.valid">
          <trim prefix="(" prefixOverrides="and" suffix=")">
            <foreach collection="criteria.criteria" item="criterion">
              <choose>
                <when test="criterion.noValue">
                  and ${criterion.condition}
                </when>
                <when test="criterion.singleValue">
                  and ${criterion.condition} #{criterion.value}
                </when>
                <when test="criterion.betweenValue">
                  and ${criterion.condition} #{criterion.value} and #{criterion.secondValue}
                </when>
                <when test="criterion.listValue">
                  and ${criterion.condition}
                  <foreach close=")" collection="criterion.value" item="listItem" open="(" separator=",">
                    #{listItem}
                  </foreach>
                </when>
              </choose>
            </foreach>
          </trim>
        </if>
      </foreach>
    </where>
  </sql>
  <sql id="Base_Column_List">
    <!--
      WARNING - @mbg.generated
      This element is automatically generated by MyBatis Generator, do not modify.
    -->
    id, descs, solution, create_date, create_time, type_id, type_name, first_type_id, 
    first_type_name, second_type_id, second_type_name, thrid_type_id, thrid_type_name, 
    source_id, source_name, creator, class_id, location, live_room, resolvor
  </sql>
  <select id="selectByExample" parameterType="com.deal.mrzhang.deal.entity.QuestionDetailExample" resultMap="BaseResultMap">
    <!--
      WARNING - @mbg.generated
      This element is automatically generated by MyBatis Generator, do not modify.
    -->
    select
    <if test="distinct">
      distinct
    </if>
    'true' as QUERYID,
    <include refid="Base_Column_List" />
    from question_detail
    <if test="_parameter != null">
      <include refid="Example_Where_Clause" />
    </if>
    <if test="orderByClause != null">
      order by ${orderByClause}
    </if>
  </select>
  <select id="selectByPrimaryKey" parameterType="java.lang.Integer" resultMap="BaseResultMap">
    <!--
      WARNING - @mbg.generated
      This element is automatically generated by MyBatis Generator, do not modify.
    -->
    select 
    <include refid="Base_Column_List" />
    from question_detail
    where id = #{id,jdbcType=INTEGER}
  </select>
  <delete id="deleteByPrimaryKey" parameterType="java.lang.Integer">
    <!--
      WARNING - @mbg.generated
      This element is automatically generated by MyBatis Generator, do not modify.
    -->
    delete from question_detail
    where id = #{id,jdbcType=INTEGER}
  </delete>
  <delete id="deleteByExample" parameterType="com.deal.mrzhang.deal.entity.QuestionDetailExample">
    <!--
      WARNING - @mbg.generated
      This element is automatically generated by MyBatis Generator, do not modify.
    -->
    delete from question_detail
    <if test="_parameter != null">
      <include refid="Example_Where_Clause" />
    </if>
  </delete>
  <insert id="insert" parameterType="com.deal.mrzhang.deal.entity.QuestionDetail">
    <!--
      WARNING - @mbg.generated
      This element is automatically generated by MyBatis Generator, do not modify.
    -->
    insert into question_detail (id, descs, solution, 
      create_date, create_time, type_id, 
      type_name, first_type_id, first_type_name, 
      second_type_id, second_type_name, thrid_type_id, 
      thrid_type_name, source_id, source_name, 
      creator, class_id, location, 
      live_room, resolvor)
    values (#{id,jdbcType=INTEGER}, #{descs,jdbcType=VARCHAR}, #{solution,jdbcType=VARCHAR}, 
      #{createDate,jdbcType=DATE}, #{createTime,jdbcType=VARCHAR}, #{typeId,jdbcType=INTEGER}, 
      #{typeName,jdbcType=VARCHAR}, #{firstTypeId,jdbcType=INTEGER}, #{firstTypeName,jdbcType=VARCHAR}, 
      #{secondTypeId,jdbcType=INTEGER}, #{secondTypeName,jdbcType=VARCHAR}, #{thridTypeId,jdbcType=INTEGER}, 
      #{thridTypeName,jdbcType=VARCHAR}, #{sourceId,jdbcType=INTEGER}, #{sourceName,jdbcType=VARCHAR}, 
      #{creator,jdbcType=VARCHAR}, #{classId,jdbcType=VARCHAR}, #{location,jdbcType=VARCHAR}, 
      #{liveRoom,jdbcType=VARCHAR}, #{resolvor,jdbcType=VARCHAR})
  </insert>
  <insert id="insertSelective" parameterType="com.deal.mrzhang.deal.entity.QuestionDetail">
    <!--
      WARNING - @mbg.generated
      This element is automatically generated by MyBatis Generator, do not modify.
    -->
    insert into question_detail
    <trim prefix="(" suffix=")" suffixOverrides=",">
      <if test="id != null">
        id,
      </if>
      <if test="descs != null">
        descs,
      </if>
      <if test="solution != null">
        solution,
      </if>
      <if test="createDate != null">
        create_date,
      </if>
      <if test="createTime != null">
        create_time,
      </if>
      <if test="typeId != null">
        type_id,
      </if>
      <if test="typeName != null">
        type_name,
      </if>
      <if test="firstTypeId != null">
        first_type_id,
      </if>
      <if test="firstTypeName != null">
        first_type_name,
      </if>
      <if test="secondTypeId != null">
        second_type_id,
      </if>
      <if test="secondTypeName != null">
        second_type_name,
      </if>
      <if test="thridTypeId != null">
        thrid_type_id,
      </if>
      <if test="thridTypeName != null">
        thrid_type_name,
      </if>
      <if test="sourceId != null">
        source_id,
      </if>
      <if test="sourceName != null">
        source_name,
      </if>
      <if test="creator != null">
        creator,
      </if>
      <if test="classId != null">
        class_id,
      </if>
      <if test="location != null">
        location,
      </if>
      <if test="liveRoom != null">
        live_room,
      </if>
      <if test="resolvor != null">
        resolvor,
      </if>
    </trim>
    <trim prefix="values (" suffix=")" suffixOverrides=",">
      <if test="id != null">
        #{id,jdbcType=INTEGER},
      </if>
      <if test="descs != null">
        #{descs,jdbcType=VARCHAR},
      </if>
      <if test="solution != null">
        #{solution,jdbcType=VARCHAR},
      </if>
      <if test="createDate != null">
        #{createDate,jdbcType=DATE},
      </if>
      <if test="createTime != null">
        #{createTime,jdbcType=VARCHAR},
      </if>
      <if test="typeId != null">
        #{typeId,jdbcType=INTEGER},
      </if>
      <if test="typeName != null">
        #{typeName,jdbcType=VARCHAR},
      </if>
      <if test="firstTypeId != null">
        #{firstTypeId,jdbcType=INTEGER},
      </if>
      <if test="firstTypeName != null">
        #{firstTypeName,jdbcType=VARCHAR},
      </if>
      <if test="secondTypeId != null">
        #{secondTypeId,jdbcType=INTEGER},
      </if>
      <if test="secondTypeName != null">
        #{secondTypeName,jdbcType=VARCHAR},
      </if>
      <if test="thridTypeId != null">
        #{thridTypeId,jdbcType=INTEGER},
      </if>
      <if test="thridTypeName != null">
        #{thridTypeName,jdbcType=VARCHAR},
      </if>
      <if test="sourceId != null">
        #{sourceId,jdbcType=INTEGER},
      </if>
      <if test="sourceName != null">
        #{sourceName,jdbcType=VARCHAR},
      </if>
      <if test="creator != null">
        #{creator,jdbcType=VARCHAR},
      </if>
      <if test="classId != null">
        #{classId,jdbcType=VARCHAR},
      </if>
      <if test="location != null">
        #{location,jdbcType=VARCHAR},
      </if>
      <if test="liveRoom != null">
        #{liveRoom,jdbcType=VARCHAR},
      </if>
      <if test="resolvor != null">
        #{resolvor,jdbcType=VARCHAR},
      </if>
    </trim>
  </insert>
  <select id="countByExample" parameterType="com.deal.mrzhang.deal.entity.QuestionDetailExample" resultType="java.lang.Long">
    <!--
      WARNING - @mbg.generated
      This element is automatically generated by MyBatis Generator, do not modify.
    -->
    select count(*) from question_detail
    <if test="_parameter != null">
      <include refid="Example_Where_Clause" />
    </if>
  </select>
  <update id="updateByExampleSelective" parameterType="map">
    <!--
      WARNING - @mbg.generated
      This element is automatically generated by MyBatis Generator, do not modify.
    -->
    update question_detail
    <set>
      <if test="record.id != null">
        id = #{record.id,jdbcType=INTEGER},
      </if>
      <if test="record.descs != null">
        descs = #{record.descs,jdbcType=VARCHAR},
      </if>
      <if test="record.solution != null">
        solution = #{record.solution,jdbcType=VARCHAR},
      </if>
      <if test="record.createDate != null">
        create_date = #{record.createDate,jdbcType=DATE},
      </if>
      <if test="record.createTime != null">
        create_time = #{record.createTime,jdbcType=VARCHAR},
      </if>
      <if test="record.typeId != null">
        type_id = #{record.typeId,jdbcType=INTEGER},
      </if>
      <if test="record.typeName != null">
        type_name = #{record.typeName,jdbcType=VARCHAR},
      </if>
      <if test="record.firstTypeId != null">
        first_type_id = #{record.firstTypeId,jdbcType=INTEGER},
      </if>
      <if test="record.firstTypeName != null">
        first_type_name = #{record.firstTypeName,jdbcType=VARCHAR},
      </if>
      <if test="record.secondTypeId != null">
        second_type_id = #{record.secondTypeId,jdbcType=INTEGER},
      </if>
      <if test="record.secondTypeName != null">
        second_type_name = #{record.secondTypeName,jdbcType=VARCHAR},
      </if>
      <if test="record.thridTypeId != null">
        thrid_type_id = #{record.thridTypeId,jdbcType=INTEGER},
      </if>
      <if test="record.thridTypeName != null">
        thrid_type_name = #{record.thridTypeName,jdbcType=VARCHAR},
      </if>
      <if test="record.sourceId != null">
        source_id = #{record.sourceId,jdbcType=INTEGER},
      </if>
      <if test="record.sourceName != null">
        source_name = #{record.sourceName,jdbcType=VARCHAR},
      </if>
      <if test="record.creator != null">
        creator = #{record.creator,jdbcType=VARCHAR},
      </if>
      <if test="record.classId != null">
        class_id = #{record.classId,jdbcType=VARCHAR},
      </if>
      <if test="record.location != null">
        location = #{record.location,jdbcType=VARCHAR},
      </if>
      <if test="record.liveRoom != null">
        live_room = #{record.liveRoom,jdbcType=VARCHAR},
      </if>
      <if test="record.resolvor != null">
        resolvor = #{record.resolvor,jdbcType=VARCHAR},
      </if>
    </set>
    <if test="_parameter != null">
      <include refid="Update_By_Example_Where_Clause" />
    </if>
  </update>
  <update id="updateByExample" parameterType="map">
    <!--
      WARNING - @mbg.generated
      This element is automatically generated by MyBatis Generator, do not modify.
    -->
    update question_detail
    set id = #{record.id,jdbcType=INTEGER},
      descs = #{record.descs,jdbcType=VARCHAR},
      solution = #{record.solution,jdbcType=VARCHAR},
      create_date = #{record.createDate,jdbcType=DATE},
      create_time = #{record.createTime,jdbcType=VARCHAR},
      type_id = #{record.typeId,jdbcType=INTEGER},
      type_name = #{record.typeName,jdbcType=VARCHAR},
      first_type_id = #{record.firstTypeId,jdbcType=INTEGER},
      first_type_name = #{record.firstTypeName,jdbcType=VARCHAR},
      second_type_id = #{record.secondTypeId,jdbcType=INTEGER},
      second_type_name = #{record.secondTypeName,jdbcType=VARCHAR},
      thrid_type_id = #{record.thridTypeId,jdbcType=INTEGER},
      thrid_type_name = #{record.thridTypeName,jdbcType=VARCHAR},
      source_id = #{record.sourceId,jdbcType=INTEGER},
      source_name = #{record.sourceName,jdbcType=VARCHAR},
      creator = #{record.creator,jdbcType=VARCHAR},
      class_id = #{record.classId,jdbcType=VARCHAR},
      location = #{record.location,jdbcType=VARCHAR},
      live_room = #{record.liveRoom,jdbcType=VARCHAR},
      resolvor = #{record.resolvor,jdbcType=VARCHAR}
    <if test="_parameter != null">
      <include refid="Update_By_Example_Where_Clause" />
    </if>
  </update>
  <update id="updateByPrimaryKeySelective" parameterType="com.deal.mrzhang.deal.entity.QuestionDetail">
    <!--
      WARNING - @mbg.generated
      This element is automatically generated by MyBatis Generator, do not modify.
    -->
    update question_detail
    <set>
      <if test="descs != null">
        descs = #{descs,jdbcType=VARCHAR},
      </if>
      <if test="solution != null">
        solution = #{solution,jdbcType=VARCHAR},
      </if>
      <if test="createDate != null">
        create_date = #{createDate,jdbcType=DATE},
      </if>
      <if test="createTime != null">
        create_time = #{createTime,jdbcType=VARCHAR},
      </if>
      <if test="typeId != null">
        type_id = #{typeId,jdbcType=INTEGER},
      </if>
      <if test="typeName != null">
        type_name = #{typeName,jdbcType=VARCHAR},
      </if>
      <if test="firstTypeId != null">
        first_type_id = #{firstTypeId,jdbcType=INTEGER},
      </if>
      <if test="firstTypeName != null">
        first_type_name = #{firstTypeName,jdbcType=VARCHAR},
      </if>
      <if test="secondTypeId != null">
        second_type_id = #{secondTypeId,jdbcType=INTEGER},
      </if>
      <if test="secondTypeName != null">
        second_type_name = #{secondTypeName,jdbcType=VARCHAR},
      </if>
      <if test="thridTypeId != null">
        thrid_type_id = #{thridTypeId,jdbcType=INTEGER},
      </if>
      <if test="thridTypeName != null">
        thrid_type_name = #{thridTypeName,jdbcType=VARCHAR},
      </if>
      <if test="sourceId != null">
        source_id = #{sourceId,jdbcType=INTEGER},
      </if>
      <if test="sourceName != null">
        source_name = #{sourceName,jdbcType=VARCHAR},
      </if>
      <if test="creator != null">
        creator = #{creator,jdbcType=VARCHAR},
      </if>
      <if test="classId != null">
        class_id = #{classId,jdbcType=VARCHAR},
      </if>
      <if test="location != null">
        location = #{location,jdbcType=VARCHAR},
      </if>
      <if test="liveRoom != null">
        live_room = #{liveRoom,jdbcType=VARCHAR},
      </if>
      <if test="resolvor != null">
        resolvor = #{resolvor,jdbcType=VARCHAR},
      </if>
    </set>
    where id = #{id,jdbcType=INTEGER}
  </update>
  <update id="updateByPrimaryKey" parameterType="com.deal.mrzhang.deal.entity.QuestionDetail">
    <!--
      WARNING - @mbg.generated
      This element is automatically generated by MyBatis Generator, do not modify.
    -->
    update question_detail
    set descs = #{descs,jdbcType=VARCHAR},
      solution = #{solution,jdbcType=VARCHAR},
      create_date = #{createDate,jdbcType=DATE},
      create_time = #{createTime,jdbcType=VARCHAR},
      type_id = #{typeId,jdbcType=INTEGER},
      type_name = #{typeName,jdbcType=VARCHAR},
      first_type_id = #{firstTypeId,jdbcType=INTEGER},
      first_type_name = #{firstTypeName,jdbcType=VARCHAR},
      second_type_id = #{secondTypeId,jdbcType=INTEGER},
      second_type_name = #{secondTypeName,jdbcType=VARCHAR},
      thrid_type_id = #{thridTypeId,jdbcType=INTEGER},
      thrid_type_name = #{thridTypeName,jdbcType=VARCHAR},
      source_id = #{sourceId,jdbcType=INTEGER},
      source_name = #{sourceName,jdbcType=VARCHAR},
      creator = #{creator,jdbcType=VARCHAR},
      class_id = #{classId,jdbcType=VARCHAR},
      location = #{location,jdbcType=VARCHAR},
      live_room = #{liveRoom,jdbcType=VARCHAR},
      resolvor = #{resolvor,jdbcType=VARCHAR}
    where id = #{id,jdbcType=INTEGER}
  </update>
</mapper>